skyperious/__init__.py
skyperious/__main__.py
skyperious/conf.py
skyperious/emoticons.py
skyperious/export.py
skyperious/gui.py
skyperious/guibase.py
skyperious/images.py
skyperious/live.py
skyperious/main.py
skyperious/searchparser.py
skyperious/skypedata.py
skyperious/skyperious.ini
skyperious/support.py
skyperious/templates.py
skyperious/workers.py
skyperious/lib/__init__.py
skyperious/lib/controls.py
skyperious/lib/util.py
skyperious/lib/wordcloud.py
skyperious/lib/wx_accel.py
skyperious/res/Carlito.ttf
skyperious/res/CarlitoBold.ttf
skyperious/res/emoticons.zip
skyperious-5.8.dist-info/LICENSE.md
skyperious-5.8.dist-info/METADATA
skyperious-5.8.dist-info/WHEEL
skyperious-5.8.dist-info/entry_points.txt
skyperious-5.8.dist-info/top_level.txt
skyperious-5.8.dist-info/RECORD
