Metadata-Version: 2.1
Name: skyperious
Version: 5.8
Summary: Skype chat history tool
Home-page: https://github.com/suurjaak/Skyperious
Author: Erki Suurjaak
Author-email: erki@lap.ee
License: MIT
Keywords: skype sqlite merge export
Platform: any
Classifier: Development Status :: 5 - Production/Stable
Classifier: Intended Audience :: End Users/Desktop
Classifier: Operating System :: Microsoft :: Windows
Classifier: Operating System :: Unix
Classifier: Operating System :: MacOS
Classifier: Topic :: Communications :: Chat
Classifier: Topic :: Database
Classifier: Topic :: Desktop Environment
Classifier: Topic :: Utilities
Classifier: License :: OSI Approved :: MIT License
Classifier: Programming Language :: Python :: 2
Classifier: Programming Language :: Python :: 2.7
Classifier: Programming Language :: Python :: 3
License-File: LICENSE.md
Requires-Dist: appdirs
Requires-Dist: beautifulsoup4
Requires-Dist: filetype
Requires-Dist: ijson
Requires-Dist: pyparsing
Requires-Dist: Pillow
Requires-Dist: six
Requires-Dist: step-template (>=0.0.4)
Requires-Dist: SkPy
Requires-Dist: wxPython (>=4.0)
Requires-Dist: XlsxWriter
